lightnlu/__init__.py
lightnlu/core/__init__.py
lightnlu/core/ner.py
lightnlu/core/rule.py
lightnlu/io/__init__.py
lightnlu/io/db/__init__.py
lightnlu/io/db/mongo.py
lightnlu/io/file/__init__.py
lightnlu/io/file/csv.py
lightnlu/io/file/json.py
lightnlu/io/file/txt.py
lightnlu/io/file/yml.py
lightnlu/utils/__init__.py
lightnlu/utils/keyword.py
lightNLU-0.2.2.dist-info/LICENSE
lightNLU-0.2.2.dist-info/METADATA
lightNLU-0.2.2.dist-info/WHEEL
lightNLU-0.2.2.dist-info/top_level.txt
lightNLU-0.2.2.dist-info/RECORD
