Metadata-Version: 2.1
Name: lightNLU
Version: 0.2.2
Summary: A lightweight natural language understanding library
Home-page: https://github.com/smilelight/lightNLU
Author: lightsmile
Author-email: iamlightsmile@gmail.com
License: Apache-2.0
Platform: UNKNOWN
Classifier: Development Status :: 4 - Beta
Classifier: Operating System :: OS Independent
Classifier: Intended Audience :: Developers
Classifier: Programming Language :: Python :: 3.7
Classifier: Programming Language :: Python :: 3.8
Classifier: Topic :: Software Development :: Libraries
Requires-Dist: lightUtils
Requires-Dist: tqdm
Requires-Dist: pymongo
